<?xml version="1.0" encoding="UTF-8"?>
<!--

  Copyright 2003 - 2011 The eFaps Team

  Licensed under the Apache License, Version 2.0 (the "License");
  you may not use this file except in compliance with the License.
  You may obtain a copy of the License at

  http://www.apache.org/licenses/LICENSE-2.0

  Unless required by applicable law or agreed to in writing, software
  distributed under the License is distributed on an "AS IS" BASIS,
  WITHOUT WARRANTIES OR CONDITIONS OF ANY KIND, either express or implied.
  See the License for the specific language governing permissions and
  limitations under the License.

  Author:          The eFaps Team
  Revision:        $Rev$
  Last Changed:    $Date$
  Last Changed By: $Author$

-->
<!--
    Datos segun Instituto Nacional de Estatistica e Informatica INEI
    Codigos de Ubicacion Geografica UBIGE (Version 2010)
-->


<import xmlns="http://www.efaps.org/xsd" xmlns:xsi="http://www.w3.org/2001/XMLSchema-instance"
    xsi:schemaLocation="http://www.efaps.org/xsd http://www.efaps.org/xsd/eFaps_1.0.xsd">
    <object type="Ubicaciones_UbicacionStandardRoot">
        <attribute name="Name">Lima</attribute>
        <attribute name="Code">150000</attribute>
        <object type="Ubicaciones_UbicacionStandard">
            <parentattribute name="ParentLink" />
            <attribute name="Name">Lima</attribute>
            <attribute name="Code">150100</attribute>
            <object type="Ubicaciones_UbicacionStandard">
                <parentattribute name="ParentLink" />
                <attribute name="Name">Lima</attribute>
                <attribute name="Code">150101</attribute>
            </object>
            <object type="Ubicaciones_UbicacionStandard">
                <parentattribute name="ParentLink" />
                <attribute name="Name">Ancon</attribute>
                <attribute name="Code">150102</attribute>
            </object>
            <object type="Ubicaciones_UbicacionStandard">
                <parentattribute name="ParentLink" />
                <attribute name="Name">Ate</attribute>
                <attribute name="Code">150103</attribute>
            </object>
            <object type="Ubicaciones_UbicacionStandard">
                <parentattribute name="ParentLink" />
                <attribute name="Name">Barranco</attribute>
                <attribute name="Code">150104</attribute>
            </object>
            <object type="Ubicaciones_UbicacionStandard">
                <parentattribute name="ParentLink" />
                <attribute name="Name">Breña</attribute>
                <attribute name="Code">150105</attribute>
            </object>
            <object type="Ubicaciones_UbicacionStandard">
                <parentattribute name="ParentLink" />
                <attribute name="Name">Carabayllo</attribute>
                <attribute name="Code">150106</attribute>
            </object>
            <object type="Ubicaciones_UbicacionStandard">
                <parentattribute name="ParentLink" />
                <attribute name="Name">Chaclacayo</attribute>
                <attribute name="Code">150107</attribute>
            </object>
            <object type="Ubicaciones_UbicacionStandard">
                <parentattribute name="ParentLink" />
                <attribute name="Name">Chorrillos</attribute>
                <attribute name="Code">150108</attribute>
            </object>
            <object type="Ubicaciones_UbicacionStandard">
                <parentattribute name="ParentLink" />
                <attribute name="Name">Cieneguilla</attribute>
                <attribute name="Code">150109</attribute>
            </object>
            <object type="Ubicaciones_UbicacionStandard">
                <parentattribute name="ParentLink" />
                <attribute name="Name">Comas</attribute>
                <attribute name="Code">150110</attribute>
            </object>
            <object type="Ubicaciones_UbicacionStandard">
                <parentattribute name="ParentLink" />
                <attribute name="Name">El Agustino</attribute>
                <attribute name="Code">150111</attribute>
            </object>
            <object type="Ubicaciones_UbicacionStandard">
                <parentattribute name="ParentLink" />
                <attribute name="Name">Independencia</attribute>
                <attribute name="Code">150112</attribute>
            </object>
            <object type="Ubicaciones_UbicacionStandard">
                <parentattribute name="ParentLink" />
                <attribute name="Name">Jesus Maria</attribute>
                <attribute name="Code">150113</attribute>
            </object>
            <object type="Ubicaciones_UbicacionStandard">
                <parentattribute name="ParentLink" />
                <attribute name="Name">La Molina</attribute>
                <attribute name="Code">150114</attribute>
            </object>
            <object type="Ubicaciones_UbicacionStandard">
                <parentattribute name="ParentLink" />
                <attribute name="Name">La Victoria</attribute>
                <attribute name="Code">150115</attribute>
            </object>
            <object type="Ubicaciones_UbicacionStandard">
                <parentattribute name="ParentLink" />
                <attribute name="Name">Lince</attribute>
                <attribute name="Code">150116</attribute>
            </object>
            <object type="Ubicaciones_UbicacionStandard">
                <parentattribute name="ParentLink" />
                <attribute name="Name">Los Olivos</attribute>
                <attribute name="Code">150117</attribute>
            </object>
            <object type="Ubicaciones_UbicacionStandard">
                <parentattribute name="ParentLink" />
                <attribute name="Name">Lurigancho-Chosica</attribute>
                <attribute name="Code">150118</attribute>
            </object>
            <object type="Ubicaciones_UbicacionStandard">
                <parentattribute name="ParentLink" />
                <attribute name="Name">Lurin</attribute>
                <attribute name="Code">150119</attribute>
            </object>
            <object type="Ubicaciones_UbicacionStandard">
                <parentattribute name="ParentLink" />
                <attribute name="Name">Magdalena Del Mar</attribute>
                <attribute name="Code">150120</attribute>
            </object>
            <object type="Ubicaciones_UbicacionStandard">
                <parentattribute name="ParentLink" />
                <attribute name="Name">Pueblo Libre</attribute>
                <attribute name="Code">150121</attribute>
            </object>
            <object type="Ubicaciones_UbicacionStandard">
                <parentattribute name="ParentLink" />
                <attribute name="Name">Miraflores</attribute>
                <attribute name="Code">150122</attribute>
            </object>
            <object type="Ubicaciones_UbicacionStandard">
                <parentattribute name="ParentLink" />
                <attribute name="Name">Pachacamac</attribute>
                <attribute name="Code">150123</attribute>
            </object>
            <object type="Ubicaciones_UbicacionStandard">
                <parentattribute name="ParentLink" />
                <attribute name="Name">Pucusana</attribute>
                <attribute name="Code">150124</attribute>
            </object>
            <object type="Ubicaciones_UbicacionStandard">
                <parentattribute name="ParentLink" />
                <attribute name="Name">Puente Piedra</attribute>
                <attribute name="Code">150125</attribute>
            </object>
            <object type="Ubicaciones_UbicacionStandard">
                <parentattribute name="ParentLink" />
                <attribute name="Name">Punta Hermosa</attribute>
                <attribute name="Code">150126</attribute>
            </object>
            <object type="Ubicaciones_UbicacionStandard">
                <parentattribute name="ParentLink" />
                <attribute name="Name">Punta Negra</attribute>
                <attribute name="Code">150127</attribute>
            </object>
            <object type="Ubicaciones_UbicacionStandard">
                <parentattribute name="ParentLink" />
                <attribute name="Name">Rimac</attribute>
                <attribute name="Code">150128</attribute>
            </object>
            <object type="Ubicaciones_UbicacionStandard">
                <parentattribute name="ParentLink" />
                <attribute name="Name">San Bartolo</attribute>
                <attribute name="Code">150129</attribute>
            </object>
            <object type="Ubicaciones_UbicacionStandard">
                <parentattribute name="ParentLink" />
                <attribute name="Name">San Borja</attribute>
                <attribute name="Code">150130</attribute>
            </object>
            <object type="Ubicaciones_UbicacionStandard">
                <parentattribute name="ParentLink" />
                <attribute name="Name">San Isidro</attribute>
                <attribute name="Code">150131</attribute>
            </object>
            <object type="Ubicaciones_UbicacionStandard">
                <parentattribute name="ParentLink" />
                <attribute name="Name">San Juan de Lurigancho</attribute>
                <attribute name="Code">150132</attribute>
            </object>
            <object type="Ubicaciones_UbicacionStandard">
                <parentattribute name="ParentLink" />
                <attribute name="Name">San Juan de Miraflores</attribute>
                <attribute name="Code">150133</attribute>
            </object>
            <object type="Ubicaciones_UbicacionStandard">
                <parentattribute name="ParentLink" />
                <attribute name="Name">San Luis</attribute>
                <attribute name="Code">150134</attribute>
            </object>
            <object type="Ubicaciones_UbicacionStandard">
                <parentattribute name="ParentLink" />
                <attribute name="Name">San Martin De Porres</attribute>
                <attribute name="Code">150135</attribute>
            </object>
            <object type="Ubicaciones_UbicacionStandard">
                <parentattribute name="ParentLink" />
                <attribute name="Name">San Miguel</attribute>
                <attribute name="Code">150136</attribute>
            </object>
            <object type="Ubicaciones_UbicacionStandard">
                <parentattribute name="ParentLink" />
                <attribute name="Name">Santa Anita</attribute>
                <attribute name="Code">150137</attribute>
            </object>
            <object type="Ubicaciones_UbicacionStandard">
                <parentattribute name="ParentLink" />
                <attribute name="Name">Santa Maria Del Mar</attribute>
                <attribute name="Code">150138</attribute>
            </object>
            <object type="Ubicaciones_UbicacionStandard">
                <parentattribute name="ParentLink" />
                <attribute name="Name">Santa Rosa</attribute>
                <attribute name="Code">150139</attribute>
            </object>
            <object type="Ubicaciones_UbicacionStandard">
                <parentattribute name="ParentLink" />
                <attribute name="Name">Santiago De Surco</attribute>
                <attribute name="Code">150140</attribute>
            </object>
            <object type="Ubicaciones_UbicacionStandard">
                <parentattribute name="ParentLink" />
                <attribute name="Name">Surquillo</attribute>
                <attribute name="Code">150141</attribute>
            </object>
            <object type="Ubicaciones_UbicacionStandard">
                <parentattribute name="ParentLink" />
                <attribute name="Name">Villa el Salvador</attribute>
                <attribute name="Code">150142</attribute>
            </object>
            <object type="Ubicaciones_UbicacionStandard">
                <parentattribute name="ParentLink" />
                <attribute name="Name">Villa Maria Del Triunfo</attribute>
                <attribute name="Code">150143</attribute>
            </object>
        </object>
        <object type="Ubicaciones_UbicacionStandard">
            <parentattribute name="ParentLink" />
            <attribute name="Name">Barranca</attribute>
            <attribute name="Code">150200</attribute>
            <object type="Ubicaciones_UbicacionStandard">
                <parentattribute name="ParentLink" />
                <attribute name="Name">Barranca</attribute>
                <attribute name="Code">150201</attribute>
            </object>
            <object type="Ubicaciones_UbicacionStandard">
                <parentattribute name="ParentLink" />
                <attribute name="Name">Paramonga</attribute>
                <attribute name="Code">150202</attribute>
            </object>
            <object type="Ubicaciones_UbicacionStandard">
                <parentattribute name="ParentLink" />
                <attribute name="Name">Pativilca</attribute>
                <attribute name="Code">150203</attribute>
            </object>
            <object type="Ubicaciones_UbicacionStandard">
                <parentattribute name="ParentLink" />
                <attribute name="Name">Supe</attribute>
                <attribute name="Code">150204</attribute>
            </object>
            <object type="Ubicaciones_UbicacionStandard">
                <parentattribute name="ParentLink" />
                <attribute name="Name">Supe Puerto</attribute>
                <attribute name="Code">150205</attribute>
            </object>
        </object>
        <object type="Ubicaciones_UbicacionStandard">
            <parentattribute name="ParentLink" />
            <attribute name="Name">Cajatambo</attribute>
            <attribute name="Code">150300</attribute>
            <object type="Ubicaciones_UbicacionStandard">
                <parentattribute name="ParentLink" />
                <attribute name="Name">Cajatambo</attribute>
                <attribute name="Code">150301</attribute>
            </object>
            <object type="Ubicaciones_UbicacionStandard">
                <parentattribute name="ParentLink" />
                <attribute name="Name">Copa</attribute>
                <attribute name="Code">150302</attribute>
            </object>
            <object type="Ubicaciones_UbicacionStandard">
                <parentattribute name="ParentLink" />
                <attribute name="Name">Gorgor</attribute>
                <attribute name="Code">150303</attribute>
            </object>
            <object type="Ubicaciones_UbicacionStandard">
                <parentattribute name="ParentLink" />
                <attribute name="Name">Huancapon</attribute>
                <attribute name="Code">150304</attribute>
            </object>
            <object type="Ubicaciones_UbicacionStandard">
                <parentattribute name="ParentLink" />
                <attribute name="Name">Manas</attribute>
                <attribute name="Code">150305</attribute>
            </object>
        </object>
        <object type="Ubicaciones_UbicacionStandard">
            <parentattribute name="ParentLink" />
            <attribute name="Name">Canta</attribute>
            <attribute name="Code">150400</attribute>
            <object type="Ubicaciones_UbicacionStandard">
                <parentattribute name="ParentLink" />
                <attribute name="Name">Canta</attribute>
                <attribute name="Code">150401</attribute>
            </object>
            <object type="Ubicaciones_UbicacionStandard">
                <parentattribute name="ParentLink" />
                <attribute name="Name">Arahuay</attribute>
                <attribute name="Code">150402</attribute>
            </object>
            <object type="Ubicaciones_UbicacionStandard">
                <parentattribute name="ParentLink" />
                <attribute name="Name">Huamantanga</attribute>
                <attribute name="Code">150403</attribute>
            </object>
            <object type="Ubicaciones_UbicacionStandard">
                <parentattribute name="ParentLink" />
                <attribute name="Name">Huaros</attribute>
                <attribute name="Code">150404</attribute>
            </object>
            <object type="Ubicaciones_UbicacionStandard">
                <parentattribute name="ParentLink" />
                <attribute name="Name">Lachaqui</attribute>
                <attribute name="Code">150405</attribute>
            </object>
            <object type="Ubicaciones_UbicacionStandard">
                <parentattribute name="ParentLink" />
                <attribute name="Name">San Buenaventura</attribute>
                <attribute name="Code">150406</attribute>
            </object>
            <object type="Ubicaciones_UbicacionStandard">
                <parentattribute name="ParentLink" />
                <attribute name="Name">Santa Rosa De Quives</attribute>
                <attribute name="Code">150407</attribute>
            </object>
        </object>
        <object type="Ubicaciones_UbicacionStandard">
            <parentattribute name="ParentLink" />
            <attribute name="Name">Cañete</attribute>
            <attribute name="Code">150500</attribute>
            <object type="Ubicaciones_UbicacionStandard">
                <parentattribute name="ParentLink" />
                <attribute name="Name">San Vicente De Cañete</attribute>
                <attribute name="Code">150501</attribute>
            </object>
            <object type="Ubicaciones_UbicacionStandard">
                <parentattribute name="ParentLink" />
                <attribute name="Name">Asia</attribute>
                <attribute name="Code">150502</attribute>
            </object>
            <object type="Ubicaciones_UbicacionStandard">
                <parentattribute name="ParentLink" />
                <attribute name="Name">Calango</attribute>
                <attribute name="Code">150503</attribute>
            </object>
            <object type="Ubicaciones_UbicacionStandard">
                <parentattribute name="ParentLink" />
                <attribute name="Name">Cerro Azul</attribute>
                <attribute name="Code">150504</attribute>
            </object>
            <object type="Ubicaciones_UbicacionStandard">
                <parentattribute name="ParentLink" />
                <attribute name="Name">Chilca</attribute>
                <attribute name="Code">150505</attribute>
            </object>
            <object type="Ubicaciones_UbicacionStandard">
                <parentattribute name="ParentLink" />
                <attribute name="Name">Coayllo</attribute>
                <attribute name="Code">150506</attribute>
            </object>
            <object type="Ubicaciones_UbicacionStandard">
                <parentattribute name="ParentLink" />
                <attribute name="Name">Imperial</attribute>
                <attribute name="Code">150507</attribute>
            </object>
            <object type="Ubicaciones_UbicacionStandard">
                <parentattribute name="ParentLink" />
                <attribute name="Name">Lunahuana</attribute>
                <attribute name="Code">150508</attribute>
            </object>
            <object type="Ubicaciones_UbicacionStandard">
                <parentattribute name="ParentLink" />
                <attribute name="Name">Mala</attribute>
                <attribute name="Code">150509</attribute>
            </object>
            <object type="Ubicaciones_UbicacionStandard">
                <parentattribute name="ParentLink" />
                <attribute name="Name">Nuevo Imperial</attribute>
                <attribute name="Code">150510</attribute>
            </object>
            <object type="Ubicaciones_UbicacionStandard">
                <parentattribute name="ParentLink" />
                <attribute name="Name">Pacaran</attribute>
                <attribute name="Code">150511</attribute>
            </object>
            <object type="Ubicaciones_UbicacionStandard">
                <parentattribute name="ParentLink" />
                <attribute name="Name">Quilmana</attribute>
                <attribute name="Code">150512</attribute>
            </object>
            <object type="Ubicaciones_UbicacionStandard">
                <parentattribute name="ParentLink" />
                <attribute name="Name">San Antonio</attribute>
                <attribute name="Code">150513</attribute>
            </object>
            <object type="Ubicaciones_UbicacionStandard">
                <parentattribute name="ParentLink" />
                <attribute name="Name">San Luis</attribute>
                <attribute name="Code">150514</attribute>
            </object>
            <object type="Ubicaciones_UbicacionStandard">
                <parentattribute name="ParentLink" />
                <attribute name="Name">Santa Cruz De Flores</attribute>
                <attribute name="Code">150515</attribute>
            </object>
            <object type="Ubicaciones_UbicacionStandard">
                <parentattribute name="ParentLink" />
                <attribute name="Name">Zuñiga</attribute>
                <attribute name="Code">150516</attribute>
            </object>
        </object>
        <object type="Ubicaciones_UbicacionStandard">
            <parentattribute name="ParentLink" />
            <attribute name="Name">Huaral</attribute>
            <attribute name="Code">150600</attribute>
            <object type="Ubicaciones_UbicacionStandard">
                <parentattribute name="ParentLink" />
                <attribute name="Name">Huaral</attribute>
                <attribute name="Code">150601</attribute>
            </object>
            <object type="Ubicaciones_UbicacionStandard">
                <parentattribute name="ParentLink" />
                <attribute name="Name">Atavillos Alto</attribute>
                <attribute name="Code">150602</attribute>
            </object>
            <object type="Ubicaciones_UbicacionStandard">
                <parentattribute name="ParentLink" />
                <attribute name="Name">Atavillos Bajo</attribute>
                <attribute name="Code">150603</attribute>
            </object>
            <object type="Ubicaciones_UbicacionStandard">
                <parentattribute name="ParentLink" />
                <attribute name="Name">Aucallama</attribute>
                <attribute name="Code">150604</attribute>
            </object>
            <object type="Ubicaciones_UbicacionStandard">
                <parentattribute name="ParentLink" />
                <attribute name="Name">Chancay</attribute>
                <attribute name="Code">150605</attribute>
            </object>
            <object type="Ubicaciones_UbicacionStandard">
                <parentattribute name="ParentLink" />
                <attribute name="Name">Ihuari</attribute>
                <attribute name="Code">150606</attribute>
            </object>
            <object type="Ubicaciones_UbicacionStandard">
                <parentattribute name="ParentLink" />
                <attribute name="Name">Lampian</attribute>
                <attribute name="Code">150607</attribute>
            </object>
            <object type="Ubicaciones_UbicacionStandard">
                <parentattribute name="ParentLink" />
                <attribute name="Name">Pacaraos</attribute>
                <attribute name="Code">150608</attribute>
            </object>
            <object type="Ubicaciones_UbicacionStandard">
                <parentattribute name="ParentLink" />
                <attribute name="Name">San Miguel De Acos</attribute>
                <attribute name="Code">150609</attribute>
            </object>
            <object type="Ubicaciones_UbicacionStandard">
                <parentattribute name="ParentLink" />
                <attribute name="Name">Santa Cruz De Andamarca</attribute>
                <attribute name="Code">150610</attribute>
            </object>
            <object type="Ubicaciones_UbicacionStandard">
                <parentattribute name="ParentLink" />
                <attribute name="Name">Sumbilca</attribute>
                <attribute name="Code">150611</attribute>
            </object>
            <object type="Ubicaciones_UbicacionStandard">
                <parentattribute name="ParentLink" />
                <attribute name="Name">Veintisiete De Noviembre</attribute>
                <attribute name="Code">150612</attribute>
            </object>
        </object>
        <object type="Ubicaciones_UbicacionStandard">
            <parentattribute name="ParentLink" />
            <attribute name="Name">Huarochiri</attribute>
            <attribute name="Code">150700</attribute>
            <object type="Ubicaciones_UbicacionStandard">
                <parentattribute name="ParentLink" />
                <attribute name="Name">Matucana</attribute>
                <attribute name="Code">150701</attribute>
            </object>
            <object type="Ubicaciones_UbicacionStandard">
                <parentattribute name="ParentLink" />
                <attribute name="Name">Antioquia</attribute>
                <attribute name="Code">150702</attribute>
            </object>
            <object type="Ubicaciones_UbicacionStandard">
                <parentattribute name="ParentLink" />
                <attribute name="Name">Callahuanca</attribute>
                <attribute name="Code">150703</attribute>
            </object>
            <object type="Ubicaciones_UbicacionStandard">
                <parentattribute name="ParentLink" />
                <attribute name="Name">Carampoma</attribute>
                <attribute name="Code">150704</attribute>
            </object>
            <object type="Ubicaciones_UbicacionStandard">
                <parentattribute name="ParentLink" />
                <attribute name="Name">Chicla</attribute>
                <attribute name="Code">150705</attribute>
            </object>
            <object type="Ubicaciones_UbicacionStandard">
                <parentattribute name="ParentLink" />
                <attribute name="Name">Cuenca</attribute>
                <attribute name="Code">150706</attribute>
            </object>
            <object type="Ubicaciones_UbicacionStandard">
                <parentattribute name="ParentLink" />
                <attribute name="Name">Huachupampa</attribute>
                <attribute name="Code">150707</attribute>
            </object>
            <object type="Ubicaciones_UbicacionStandard">
                <parentattribute name="ParentLink" />
                <attribute name="Name">Huanza</attribute>
                <attribute name="Code">150708</attribute>
            </object>
            <object type="Ubicaciones_UbicacionStandard">
                <parentattribute name="ParentLink" />
                <attribute name="Name">Huarochiri</attribute>
                <attribute name="Code">150709</attribute>
            </object>
            <object type="Ubicaciones_UbicacionStandard">
                <parentattribute name="ParentLink" />
                <attribute name="Name">Lahuaytambo</attribute>
                <attribute name="Code">150710</attribute>
            </object>
            <object type="Ubicaciones_UbicacionStandard">
                <parentattribute name="ParentLink" />
                <attribute name="Name">Langa</attribute>
                <attribute name="Code">150711</attribute>
            </object>
            <object type="Ubicaciones_UbicacionStandard">
                <parentattribute name="ParentLink" />
                <attribute name="Name">Laraos</attribute>
                <attribute name="Code">150712</attribute>
            </object>
            <object type="Ubicaciones_UbicacionStandard">
                <parentattribute name="ParentLink" />
                <attribute name="Name">Mariatana</attribute>
                <attribute name="Code">150713</attribute>
            </object>
            <object type="Ubicaciones_UbicacionStandard">
                <parentattribute name="ParentLink" />
                <attribute name="Name">Ricardo Palma</attribute>
                <attribute name="Code">150714</attribute>
            </object>
            <object type="Ubicaciones_UbicacionStandard">
                <parentattribute name="ParentLink" />
                <attribute name="Name">San Andres De Tupicocha</attribute>
                <attribute name="Code">150715</attribute>
            </object>
            <object type="Ubicaciones_UbicacionStandard">
                <parentattribute name="ParentLink" />
                <attribute name="Name">San Antonio</attribute>
                <attribute name="Code">150716</attribute>
            </object>
            <object type="Ubicaciones_UbicacionStandard">
                <parentattribute name="ParentLink" />
                <attribute name="Name">San Bartolome</attribute>
                <attribute name="Code">150717</attribute>
            </object>
            <object type="Ubicaciones_UbicacionStandard">
                <parentattribute name="ParentLink" />
                <attribute name="Name">San Damian</attribute>
                <attribute name="Code">150718</attribute>
            </object>
            <object type="Ubicaciones_UbicacionStandard">
                <parentattribute name="ParentLink" />
                <attribute name="Name">San Juan De Iris</attribute>
                <attribute name="Code">150719</attribute>
            </object>
            <object type="Ubicaciones_UbicacionStandard">
                <parentattribute name="ParentLink" />
                <attribute name="Name">San Juan De Tantaranche</attribute>
                <attribute name="Code">150720</attribute>
            </object>
            <object type="Ubicaciones_UbicacionStandard">
                <parentattribute name="ParentLink" />
                <attribute name="Name">San Lorenzo De Quinti</attribute>
                <attribute name="Code">150721</attribute>
            </object>
            <object type="Ubicaciones_UbicacionStandard">
                <parentattribute name="ParentLink" />
                <attribute name="Name">San Mateo</attribute>
                <attribute name="Code">150722</attribute>
            </object>
            <object type="Ubicaciones_UbicacionStandard">
                <parentattribute name="ParentLink" />
                <attribute name="Name">San Mateo De Otao</attribute>
                <attribute name="Code">150723</attribute>
            </object>
            <object type="Ubicaciones_UbicacionStandard">
                <parentattribute name="ParentLink" />
                <attribute name="Name">San Pedro De Casta</attribute>
                <attribute name="Code">150724</attribute>
            </object>
            <object type="Ubicaciones_UbicacionStandard">
                <parentattribute name="ParentLink" />
                <attribute name="Name">San Pedro De Huancayre</attribute>
                <attribute name="Code">150725</attribute>
            </object>
            <object type="Ubicaciones_UbicacionStandard">
                <parentattribute name="ParentLink" />
                <attribute name="Name">Sangallaya</attribute>
                <attribute name="Code">150726</attribute>
            </object>
            <object type="Ubicaciones_UbicacionStandard">
                <parentattribute name="ParentLink" />
                <attribute name="Name">Santa Cruz de Cocachacra</attribute>
                <attribute name="Code">150727</attribute>
            </object>
            <object type="Ubicaciones_UbicacionStandard">
                <parentattribute name="ParentLink" />
                <attribute name="Name">Santa Eulalia</attribute>
                <attribute name="Code">150728</attribute>
            </object>
            <object type="Ubicaciones_UbicacionStandard">
                <parentattribute name="ParentLink" />
                <attribute name="Name">Santiago De Anchucaya</attribute>
                <attribute name="Code">150729</attribute>
            </object>
            <object type="Ubicaciones_UbicacionStandard">
                <parentattribute name="ParentLink" />
                <attribute name="Name">Santiago De Tuna</attribute>
                <attribute name="Code">150730</attribute>
            </object>
            <object type="Ubicaciones_UbicacionStandard">
                <parentattribute name="ParentLink" />
                <attribute name="Name">Santo Domingo De Los Olleros</attribute>
                <attribute name="Code">150731</attribute>
            </object>
            <object type="Ubicaciones_UbicacionStandard">
                <parentattribute name="ParentLink" />
                <attribute name="Name">Surco</attribute>
                <attribute name="Code">150732</attribute>
            </object>
        </object>
        <object type="Ubicaciones_UbicacionStandard">
            <parentattribute name="ParentLink" />
            <attribute name="Name">Huaura</attribute>
            <attribute name="Code">150800</attribute>
            <object type="Ubicaciones_UbicacionStandard">
                <parentattribute name="ParentLink" />
                <attribute name="Name">Huacho</attribute>
                <attribute name="Code">150801</attribute>
            </object>
            <object type="Ubicaciones_UbicacionStandard">
                <parentattribute name="ParentLink" />
                <attribute name="Name">Ambar</attribute>
                <attribute name="Code">150802</attribute>
            </object>
            <object type="Ubicaciones_UbicacionStandard">
                <parentattribute name="ParentLink" />
                <attribute name="Name">Caleta De Carquin</attribute>
                <attribute name="Code">150803</attribute>
            </object>
            <object type="Ubicaciones_UbicacionStandard">
                <parentattribute name="ParentLink" />
                <attribute name="Name">Checras</attribute>
                <attribute name="Code">150804</attribute>
            </object>
            <object type="Ubicaciones_UbicacionStandard">
                <parentattribute name="ParentLink" />
                <attribute name="Name">Hualmay</attribute>
                <attribute name="Code">150805</attribute>
            </object>
            <object type="Ubicaciones_UbicacionStandard">
                <parentattribute name="ParentLink" />
                <attribute name="Name">Huaura</attribute>
                <attribute name="Code">150806</attribute>
            </object>
            <object type="Ubicaciones_UbicacionStandard">
                <parentattribute name="ParentLink" />
                <attribute name="Name">Leoncio Prado</attribute>
                <attribute name="Code">150807</attribute>
            </object>
            <object type="Ubicaciones_UbicacionStandard">
                <parentattribute name="ParentLink" />
                <attribute name="Name">Paccho</attribute>
                <attribute name="Code">150808</attribute>
            </object>
            <object type="Ubicaciones_UbicacionStandard">
                <parentattribute name="ParentLink" />
                <attribute name="Name">Santa Leonor</attribute>
                <attribute name="Code">150809</attribute>
            </object>
            <object type="Ubicaciones_UbicacionStandard">
                <parentattribute name="ParentLink" />
                <attribute name="Name">Santa Maria</attribute>
                <attribute name="Code">150810</attribute>
            </object>
            <object type="Ubicaciones_UbicacionStandard">
                <parentattribute name="ParentLink" />
                <attribute name="Name">Sayan</attribute>
                <attribute name="Code">150811</attribute>
            </object>
            <object type="Ubicaciones_UbicacionStandard">
                <parentattribute name="ParentLink" />
                <attribute name="Name">Vegueta</attribute>
                <attribute name="Code">150812</attribute>
            </object>
        </object>
        <object type="Ubicaciones_UbicacionStandard">
            <parentattribute name="ParentLink" />
            <attribute name="Name">Oyon</attribute>
            <attribute name="Code">150900</attribute>
            <object type="Ubicaciones_UbicacionStandard">
                <parentattribute name="ParentLink" />
                <attribute name="Name">Oyon</attribute>
                <attribute name="Code">150901</attribute>
            </object>
            <object type="Ubicaciones_UbicacionStandard">
                <parentattribute name="ParentLink" />
                <attribute name="Name">Andajes</attribute>
                <attribute name="Code">150902</attribute>
            </object>
            <object type="Ubicaciones_UbicacionStandard">
                <parentattribute name="ParentLink" />
                <attribute name="Name">Caujul</attribute>
                <attribute name="Code">150903</attribute>
            </object>
            <object type="Ubicaciones_UbicacionStandard">
                <parentattribute name="ParentLink" />
                <attribute name="Name">Cochamarca</attribute>
                <attribute name="Code">150904</attribute>
            </object>
            <object type="Ubicaciones_UbicacionStandard">
                <parentattribute name="ParentLink" />
                <attribute name="Name">Navan</attribute>
                <attribute name="Code">150905</attribute>
            </object>
            <object type="Ubicaciones_UbicacionStandard">
                <parentattribute name="ParentLink" />
                <attribute name="Name">Pachangara</attribute>
                <attribute name="Code">150906</attribute>
            </object>
        </object>
        <object type="Ubicaciones_UbicacionStandard">
            <parentattribute name="ParentLink" />
            <attribute name="Name">Yauyos</attribute>
            <attribute name="Code">151000</attribute>
            <object type="Ubicaciones_UbicacionStandard">
                <parentattribute name="ParentLink" />
                <attribute name="Name">Yauyos</attribute>
                <attribute name="Code">151001</attribute>
            </object>
            <object type="Ubicaciones_UbicacionStandard">
                <parentattribute name="ParentLink" />
                <attribute name="Name">Alis</attribute>
                <attribute name="Code">151002</attribute>
            </object>
            <object type="Ubicaciones_UbicacionStandard">
                <parentattribute name="ParentLink" />
                <attribute name="Name">Ayauca</attribute>
                <attribute name="Code">151003</attribute>
            </object>
            <object type="Ubicaciones_UbicacionStandard">
                <parentattribute name="ParentLink" />
                <attribute name="Name">Ayaviri</attribute>
                <attribute name="Code">151004</attribute>
            </object>
            <object type="Ubicaciones_UbicacionStandard">
                <parentattribute name="ParentLink" />
                <attribute name="Name">Azangaro</attribute>
                <attribute name="Code">151005</attribute>
            </object>
            <object type="Ubicaciones_UbicacionStandard">
                <parentattribute name="ParentLink" />
                <attribute name="Name">Cacra</attribute>
                <attribute name="Code">151006</attribute>
            </object>
            <object type="Ubicaciones_UbicacionStandard">
                <parentattribute name="ParentLink" />
                <attribute name="Name">Carania</attribute>
                <attribute name="Code">151007</attribute>
            </object>
            <object type="Ubicaciones_UbicacionStandard">
                <parentattribute name="ParentLink" />
                <attribute name="Name">Catahuasi</attribute>
                <attribute name="Code">151008</attribute>
            </object>
            <object type="Ubicaciones_UbicacionStandard">
                <parentattribute name="ParentLink" />
                <attribute name="Name">Chocos</attribute>
                <attribute name="Code">151009</attribute>
            </object>
            <object type="Ubicaciones_UbicacionStandard">
                <parentattribute name="ParentLink" />
                <attribute name="Name">Cochas</attribute>
                <attribute name="Code">151010</attribute>
            </object>
            <object type="Ubicaciones_UbicacionStandard">
                <parentattribute name="ParentLink" />
                <attribute name="Name">Colonia</attribute>
                <attribute name="Code">151011</attribute>
            </object>
            <object type="Ubicaciones_UbicacionStandard">
                <parentattribute name="ParentLink" />
                <attribute name="Name">Hongos</attribute>
                <attribute name="Code">151012</attribute>
            </object>
            <object type="Ubicaciones_UbicacionStandard">
                <parentattribute name="ParentLink" />
                <attribute name="Name">Huampara</attribute>
                <attribute name="Code">151013</attribute>
            </object>
            <object type="Ubicaciones_UbicacionStandard">
                <parentattribute name="ParentLink" />
                <attribute name="Name">Huancaya</attribute>
                <attribute name="Code">151014</attribute>
            </object>
            <object type="Ubicaciones_UbicacionStandard">
                <parentattribute name="ParentLink" />
                <attribute name="Name">Huangascar</attribute>
                <attribute name="Code">151015</attribute>
            </object>
            <object type="Ubicaciones_UbicacionStandard">
                <parentattribute name="ParentLink" />
                <attribute name="Name">Huantan</attribute>
                <attribute name="Code">151016</attribute>
            </object>
            <object type="Ubicaciones_UbicacionStandard">
                <parentattribute name="ParentLink" />
                <attribute name="Name">Huañec</attribute>
                <attribute name="Code">151017</attribute>
            </object>
            <object type="Ubicaciones_UbicacionStandard">
                <parentattribute name="ParentLink" />
                <attribute name="Name">Laraos</attribute>
                <attribute name="Code">151018</attribute>
            </object>
            <object type="Ubicaciones_UbicacionStandard">
                <parentattribute name="ParentLink" />
                <attribute name="Name">Lincha</attribute>
                <attribute name="Code">151019</attribute>
            </object>
            <object type="Ubicaciones_UbicacionStandard">
                <parentattribute name="ParentLink" />
                <attribute name="Name">Madean</attribute>
                <attribute name="Code">151020</attribute>
            </object>
            <object type="Ubicaciones_UbicacionStandard">
                <parentattribute name="ParentLink" />
                <attribute name="Name">Miraflores</attribute>
                <attribute name="Code">151021</attribute>
            </object>
            <object type="Ubicaciones_UbicacionStandard">
                <parentattribute name="ParentLink" />
                <attribute name="Name">Omas</attribute>
                <attribute name="Code">151022</attribute>
            </object>
            <object type="Ubicaciones_UbicacionStandard">
                <parentattribute name="ParentLink" />
                <attribute name="Name">Putinza</attribute>
                <attribute name="Code">151023</attribute>
            </object>
            <object type="Ubicaciones_UbicacionStandard">
                <parentattribute name="ParentLink" />
                <attribute name="Name">Quinches</attribute>
                <attribute name="Code">151024</attribute>
            </object>
            <object type="Ubicaciones_UbicacionStandard">
                <parentattribute name="ParentLink" />
                <attribute name="Name">Quinocay</attribute>
                <attribute name="Code">151025</attribute>
            </object>
            <object type="Ubicaciones_UbicacionStandard">
                <parentattribute name="ParentLink" />
                <attribute name="Name">San Joaquin</attribute>
                <attribute name="Code">151026</attribute>
            </object>
            <object type="Ubicaciones_UbicacionStandard">
                <parentattribute name="ParentLink" />
                <attribute name="Name">San Pedro De Pilas</attribute>
                <attribute name="Code">151027</attribute>
            </object>
            <object type="Ubicaciones_UbicacionStandard">
                <parentattribute name="ParentLink" />
                <attribute name="Name">Tanta</attribute>
                <attribute name="Code">151028</attribute>
            </object>
            <object type="Ubicaciones_UbicacionStandard">
                <parentattribute name="ParentLink" />
                <attribute name="Name">Tauripampa</attribute>
                <attribute name="Code">151029</attribute>
            </object>
            <object type="Ubicaciones_UbicacionStandard">
                <parentattribute name="ParentLink" />
                <attribute name="Name">Tomas</attribute>
                <attribute name="Code">151030</attribute>
            </object>
            <object type="Ubicaciones_UbicacionStandard">
                <parentattribute name="ParentLink" />
                <attribute name="Name">Tupe</attribute>
                <attribute name="Code">151031</attribute>
            </object>
            <object type="Ubicaciones_UbicacionStandard">
                <parentattribute name="ParentLink" />
                <attribute name="Name">Viñac</attribute>
                <attribute name="Code">151032</attribute>
            </object>
            <object type="Ubicaciones_UbicacionStandard">
                <parentattribute name="ParentLink" />
                <attribute name="Name">Vitis</attribute>
                <attribute name="Code">15103</attribute>
            </object>
        </object>
    </object>
</import>
