<?xml version="1.0" encoding="UTF-8"?>
<!--

  Copyright 2003 - 2011 The eFaps Team

  Licensed under the Apache License, Version 2.0 (the "License");
  you may not use this file except in compliance with the License.
  You may obtain a copy of the License at

  http://www.apache.org/licenses/LICENSE-2.0

  Unless required by applicable law or agreed to in writing, software
  distributed under the License is distributed on an "AS IS" BASIS,
  WITHOUT WARRANTIES OR CONDITIONS OF ANY KIND, either express or implied.
  See the License for the specific language governing permissions and
  limitations under the License.

  Author:          The eFaps Team
  Revision:        $Rev$
  Last Changed:    $Date$
  Last Changed By: $Author$

-->
<import xmlns="http://www.efaps.org/xsd"
    xmlns:xsi="http://www.w3.org/2001/XMLSchema-instance"
    xsi:schemaLocation="http://www.efaps.org/xsd http://www.efaps.org/xsd/eFaps_1.0.xsd">
    <object type="Ubicaciones_UbicacionStandardRoot">
        <attribute name="Name">Ica</attribute>
        <object type="Ubicaciones_UbicacionStandard">
            <parentattribute name="ParentLink"/>
            <attribute name="Name">Ica</attribute>
            <object type="Ubicaciones_UbicacionStandard">
                <parentattribute name="ParentLink"/>
                <attribute name="Name">Ica</attribute>
            </object>
            <object type="Ubicaciones_UbicacionStandard">
                <parentattribute name="ParentLink"/>
                <attribute name="Name">La Tinguiña</attribute>
            </object>
            <object type="Ubicaciones_UbicacionStandard">
                <parentattribute name="ParentLink"/>
                <attribute name="Name">Los Aquijes</attribute>
            </object>
            <object type="Ubicaciones_UbicacionStandard">
                <parentattribute name="ParentLink"/>
                <attribute name="Name">Ocucaje</attribute>
            </object>
            <object type="Ubicaciones_UbicacionStandard">
                <parentattribute name="ParentLink"/>
                <attribute name="Name">Pachacutec</attribute>
            </object>
            <object type="Ubicaciones_UbicacionStandard">
                <parentattribute name="ParentLink"/>
                <attribute name="Name">Parcona</attribute>
            </object>
            <object type="Ubicaciones_UbicacionStandard">
                <parentattribute name="ParentLink"/>
                <attribute name="Name">Pueblo Nuevo</attribute>
            </object>
            <object type="Ubicaciones_UbicacionStandard">
                <parentattribute name="ParentLink"/>
                <attribute name="Name">Salas</attribute>
            </object>
            <object type="Ubicaciones_UbicacionStandard">
                <parentattribute name="ParentLink"/>
                <attribute name="Name">San Jose De Los Molinos</attribute>
            </object>
            <object type="Ubicaciones_UbicacionStandard">
                <parentattribute name="ParentLink"/>
                <attribute name="Name">San Juan Bautista</attribute>
            </object>
            <object type="Ubicaciones_UbicacionStandard">
                <parentattribute name="ParentLink"/>
                <attribute name="Name">Santiago</attribute>
            </object>
            <object type="Ubicaciones_UbicacionStandard">
                <parentattribute name="ParentLink"/>
                <attribute name="Name">Subtanjalla</attribute>
            </object>
            <object type="Ubicaciones_UbicacionStandard">
                <parentattribute name="ParentLink"/>
                <attribute name="Name">Tate</attribute>
            </object>
            <object type="Ubicaciones_UbicacionStandard">
                <parentattribute name="ParentLink"/>
                <attribute name="Name">Yauca Del Rosario</attribute>
            </object>
        </object>
        <object type="Ubicaciones_UbicacionStandard">
            <parentattribute name="ParentLink"/>
            <attribute name="Name">Chincha</attribute>
            <object type="Ubicaciones_UbicacionStandard">
                <parentattribute name="ParentLink"/>
                <attribute name="Name">Chincha Alta</attribute>
            </object>
            <object type="Ubicaciones_UbicacionStandard">
                <parentattribute name="ParentLink"/>
                <attribute name="Name">Alto Laran</attribute>
            </object>
            <object type="Ubicaciones_UbicacionStandard">
                <parentattribute name="ParentLink"/>
                <attribute name="Name">Chavin</attribute>
            </object>
            <object type="Ubicaciones_UbicacionStandard">
                <parentattribute name="ParentLink"/>
                <attribute name="Name">Chincha Baja</attribute>
            </object>
            <object type="Ubicaciones_UbicacionStandard">
                <parentattribute name="ParentLink"/>
                <attribute name="Name">El Carmen</attribute>
            </object>
            <object type="Ubicaciones_UbicacionStandard">
                <parentattribute name="ParentLink"/>
                <attribute name="Name">Grocio Prado</attribute>
            </object>
            <object type="Ubicaciones_UbicacionStandard">
                <parentattribute name="ParentLink"/>
                <attribute name="Name">Pueblo Nuevo</attribute>
            </object>
            <object type="Ubicaciones_UbicacionStandard">
                <parentattribute name="ParentLink"/>
                <attribute name="Name">San Juan De Yanac</attribute>
            </object>
            <object type="Ubicaciones_UbicacionStandard">
                <parentattribute name="ParentLink"/>
                <attribute name="Name">San Pedro De Huacarpana</attribute>
            </object>
            <object type="Ubicaciones_UbicacionStandard">
                <parentattribute name="ParentLink"/>
                <attribute name="Name">Sunampe</attribute>
            </object>
            <object type="Ubicaciones_UbicacionStandard">
                <parentattribute name="ParentLink"/>
                <attribute name="Name">Tambo De Mora</attribute>
            </object>
        </object>
        <object type="Ubicaciones_UbicacionStandard">
            <parentattribute name="ParentLink"/>
            <attribute name="Name">Nazca</attribute>
            <object type="Ubicaciones_UbicacionStandard">
                <parentattribute name="ParentLink"/>
                <attribute name="Name">Nazca</attribute>
            </object>
            <object type="Ubicaciones_UbicacionStandard">
                <parentattribute name="ParentLink"/>
                <attribute name="Name">Changuillo</attribute>
            </object>
            <object type="Ubicaciones_UbicacionStandard">
                <parentattribute name="ParentLink"/>
                <attribute name="Name">El Ingenio</attribute>
            </object>
            <object type="Ubicaciones_UbicacionStandard">
                <parentattribute name="ParentLink"/>
                <attribute name="Name">Marcona</attribute>
            </object>
            <object type="Ubicaciones_UbicacionStandard">
                <parentattribute name="ParentLink"/>
                <attribute name="Name">Vista Alegre</attribute>
            </object>
        </object>
        <object type="Ubicaciones_UbicacionStandard">
            <parentattribute name="ParentLink"/>
            <attribute name="Name">Palpa</attribute>
            <object type="Ubicaciones_UbicacionStandard">
                <parentattribute name="ParentLink"/>
                <attribute name="Name">Palpa</attribute>
            </object>
            <object type="Ubicaciones_UbicacionStandard">
                <parentattribute name="ParentLink"/>
                <attribute name="Name">Llipata</attribute>
            </object>
            <object type="Ubicaciones_UbicacionStandard">
                <parentattribute name="ParentLink"/>
                <attribute name="Name">Rio Grande</attribute>
            </object>
            <object type="Ubicaciones_UbicacionStandard">
                <parentattribute name="ParentLink"/>
                <attribute name="Name">Santa Cruz</attribute>
            </object>
            <object type="Ubicaciones_UbicacionStandard">
                <parentattribute name="ParentLink"/>
                <attribute name="Name">Tibillo</attribute>
            </object>
        </object>
        <object type="Ubicaciones_UbicacionStandard">
            <parentattribute name="ParentLink"/>
            <attribute name="Name">Pisco</attribute>
            <object type="Ubicaciones_UbicacionStandard">
                <parentattribute name="ParentLink"/>
                <attribute name="Name">Pisco</attribute>
            </object>
            <object type="Ubicaciones_UbicacionStandard">
                <parentattribute name="ParentLink"/>
                <attribute name="Name">Huancano</attribute>
            </object>
            <object type="Ubicaciones_UbicacionStandard">
                <parentattribute name="ParentLink"/>
                <attribute name="Name">Humay</attribute>
            </object>
            <object type="Ubicaciones_UbicacionStandard">
                <parentattribute name="ParentLink"/>
                <attribute name="Name">Independencia</attribute>
            </object>
            <object type="Ubicaciones_UbicacionStandard">
                <parentattribute name="ParentLink"/>
                <attribute name="Name">Paracas</attribute>
            </object>
            <object type="Ubicaciones_UbicacionStandard">
                <parentattribute name="ParentLink"/>
                <attribute name="Name">San Andres</attribute>
            </object>
            <object type="Ubicaciones_UbicacionStandard">
                <parentattribute name="ParentLink"/>
                <attribute name="Name">San Clemente</attribute>
            </object>
            <object type="Ubicaciones_UbicacionStandard">
                <parentattribute name="ParentLink"/>
                <attribute name="Name">Tupac Amaru Inca</attribute>
            </object>
        </object>
    </object>
</import>
